{
  "type": "minecraft:chest",
  "pools": [
    {
      "rolls": 2,
      "bonus_rolls": 0,
      "entries": [
        {
          "type": "minecraft:item",
          "name": "minecraft:wheat_seeds",
          "functions": [
            {
              "function": "minecraft:set_count",
              "count": 4
            }
          ]
        },
        {
          "type": "minecraft:item",
          "name": "minecraft:bread",
          "functions": [
            {
              "function": "minecraft:set_count",
              "count": 4
            }
          ]
        }
      ]
    },
    {
      "rolls": {
        "min": 2,
        "max": 4
      },
      "bonus_rolls": 1,
      "entries": [
        {
          "type": "minecraft:item",
          "name": "minecraft:copper_ingot",
          "functions": [
            {
              "function": "minecraft:set_count",
              "count": {
                "min": 3,
                "max": 12
              },
              "add": true
            }
          ]
        },
        {
          "type": "minecraft:item",
          "name": "minecraft:obsidian",
          "functions": [
            {
              "function": "minecraft:set_count",
              "count": 2
            }
          ]
        },
        {
          "type": "minecraft:item",
          "name": "datanessence:essence_shard",
          "functions": [
            {
              "function": "minecraft:set_count",
              "count": {
                "min": 4,
                "max": 8
              }
            }
          ],
          "conditions": []
        }
      ]
    }
  ]
}