{
  "type": "oritech:resource_node",
  "config": {
    "nodeSize": 6,
    "nodeOreChance": 0.3,
    "boulderRadius": 2,
    "nodeOres": [
      "oritech:resource_node_gold",
      "oritech:resource_node_nickel",
      "oritech:resource_node_lapis",
      "oritech:resource_node_lapis",
      "oritech:resource_node_redstone",
      "oritech:resource_node_redstone",
      "oritech:resource_node_redstone"
    ],
    "boulderOres": [
      "minecraft:gold_ore",
      "minecraft:lapis_ore",
      "minecraft:redstone_ore",
      "minecraft:stone",
      "minecraft:stone",
      "minecraft:stone",
      "minecraft:stone",
      "minecraft:stone"
    ],
    "overlayBlock": "oritech:still_oil_block",
    "overlayHeight": 5
  }
}